{
  "db_name": "PostgreSQL",
  "query": "\n\t\tSELECT block_hash, block_vote_minimum, block_vote_source FROM blocks where block_hash = ANY($1)\n\t\t",
  "describe": {
    "columns": [
      {
        "ordinal": 0,
        "name": "block_hash",
        "type_info": "Bytea"
      },
      {
        "ordinal": 1,
        "name": "block_vote_minimum",
        "type_info": "Varchar"
      },
      {
        "ordinal": 2,
        "name": "block_vote_source",
        "type_info": "Int4"
      }
    ],
    "parameters": {
      "Left": [
        "ByteaArray"
      ]
    },
    "nullable": [
      false,
      false,
      false
    ]
  },
  "hash": "4b8fda16252fc134cbb744361fde0a7e73bd7e9094ee56dedf8164ca031492b3"
}
